yate/__init__.py
yate/__main__.py
yate/errors.py
yate/lexer.py
yate/nodes.py
yate/tokens.py
yate/utils.py
yate_engine-1.0.2.dist-info/LICENSE
yate_engine-1.0.2.dist-info/METADATA
yate_engine-1.0.2.dist-info/WHEEL
yate_engine-1.0.2.dist-info/top_level.txt
yate_engine-1.0.2.dist-info/RECORD
